pyrail/__init__.py
pyrail/irail.py
pyrail/models.py
pyrail/py.typed
pyrail-0.3.0.dist-info/LICENSE
pyrail-0.3.0.dist-info/METADATA
pyrail-0.3.0.dist-info/WHEEL
pyrail-0.3.0.dist-info/RECORD
