Metadata-Version: 2.3
Name: pyrail
Version: 0.3.0
Summary: A Python wrapper for the iRail API
License: Apache-2.0
Keywords: irail,nmbs
Author: Jorim Tielemans
Author-email: tielemans.jorim@gmail.com
Requires-Python: >=3.12,<4.0
Classifier: License :: OSI Approved :: Apache Software License
Classifier: Programming Language :: Python :: 3
Classifier: Programming Language :: Python :: 3.12
Classifier: Programming Language :: Python :: 3.13
Classifier: Topic :: Software Development :: Libraries :: Python Modules
Requires-Dist: aiohttp (>=3.11.11,<4.0.0)
Requires-Dist: mashumaro[orjson] (>=3.15,<4.0)
Project-URL: Documentation, https://github.com/tjorim/pyrail
Project-URL: Homepage, https://github.com/tjorim/pyrail
Project-URL: Repository, https://github.com/tjorim/pyrail
